intake_sdmx.py
intake_sdmx-0.2.1.dist-info/entry_points.txt
intake_sdmx-0.2.1.dist-info/LICENSE
intake_sdmx-0.2.1.dist-info/WHEEL
intake_sdmx-0.2.1.dist-info/METADATA
intake_sdmx-0.2.1.dist-info/RECORD
