Metadata-Version: 2.1
Name: intake_sdmx
Version: 0.2.1
Summary: intake plugin for SDMX data sources
Home-page: https://github.com/dr-leo/pandasdmx
Keywords: statistics, SDMX, intake, data, economics, science, plot
Author: dr-leo
Author-email: fhaxbox66@gmail.com
Requires-Python: >=3.7.8,<4
Classifier: Intended Audience :: Developers
Classifier: Intended Audience :: Science/Research
Classifier: Intended Audience :: Financial and Insurance Industry
Classifier: Development Status :: 4 - Beta
Classifier: Operating System :: OS Independent
Classifier: Programming Language :: Python :: 3
Classifier: Programming Language :: Python :: 3.7
Classifier: Programming Language :: Python :: 3.8
Classifier: Programming Language :: Python :: 3.9
Classifier: Programming Language :: Python :: 3.10
Classifier: Topic :: Scientific/Engineering
Classifier: Topic :: Scientific/Engineering :: Information Analysis
Classifier: License :: OSI Approved :: Apache Software License
Requires-Dist: pandasdmx[cache] >= 1.7.0
Requires-Dist: intake >= 0.6.5
Requires-Dist: sphinx >= 3.4 ; extra == "doc"
Requires-Dist: IPython ; extra == "doc"
Requires-Dist: pytest >= 5 ; extra == "test"
Project-URL: Documentation, https://intake_sdmx.readthedocs.io/
Provides-Extra: doc
Provides-Extra: test
